setup.py
vkstreaming/__init__.py
vkstreaming/core.py
vkstreaming.egg-info/PKG-INFO
vkstreaming.egg-info/SOURCES.txt
vkstreaming.egg-info/dependency_links.txt
vkstreaming.egg-info/requires.txt
vkstreaming.egg-info/top_level.txt