Metadata-Version: 1.1
Name: vkstreaming
Version: 0.4
Summary: vk streaming API Python
Home-page: https://github.com/SevereCloud/vk-streaming
Author: Daniil Suvorov
Author-email: severecloud@gmail.com
License: MIT License
Download-URL: https://github.com/SevereCloud/vk-streaming/archive/master.zip
Keywords: vk.com vk streaming api
Platform: UNKNOWN
Classifier: Environment :: Web Environment
Classifier: Intended Audience :: Developers
Classifier: License :: OSI Approved :: MIT License
Classifier: Programming Language :: Python
Classifier: Programming Language :: Python :: 2
Classifier: Programming Language :: Python :: 3
